osint_cli_tool_skeleton/__init__.py
osint_cli_tool_skeleton/__main__.py
osint_cli_tool_skeleton/_version.py
osint_cli_tool_skeleton/cli.py
osint_cli_tool_skeleton/core.py
osint_cli_tool_skeleton/executor.py
osint_cli_tool_skeleton/report.py
osint_cli_tool_skeleton-0.0.3.dist-info/LICENSE
osint_cli_tool_skeleton-0.0.3.dist-info/METADATA
osint_cli_tool_skeleton-0.0.3.dist-info/WHEEL
osint_cli_tool_skeleton-0.0.3.dist-info/entry_points.txt
osint_cli_tool_skeleton-0.0.3.dist-info/top_level.txt
osint_cli_tool_skeleton-0.0.3.dist-info/RECORD
