Metadata-Version: 2.1
Name: osint-cli-tool-skeleton
Version: 0.0.3
Summary: A skeleton for OSINT CLI tool
Home-page: https://github.com/soxoj/osint-cli-tool-skeleton
Author: Soxoj
Author-email: soxoj@protonmail.com
License: MIT
Platform: UNKNOWN
License-File: LICENSE
Requires-Dist: asyncio (==3.4.3)
Requires-Dist: tqdm (==4.62.3)
Requires-Dist: colorama (==0.4.4)
Requires-Dist: termcolor (==1.1.0)
